luxgeo/__init__.py
luxgeo/api.py
luxgeo/auth.py
luxgeo/helpers.py
luxgeo/main.py
luxgeo-0.1.2.dist-info/licenses/LICENSE
luxgeo-0.1.2.dist-info/METADATA
luxgeo-0.1.2.dist-info/WHEEL
luxgeo-0.1.2.dist-info/top_level.txt
luxgeo-0.1.2.dist-info/RECORD
