Metadata-Version: 2.4
Name: luxgeo
Version: 0.1.2
Summary: A very basic Python API for Lux Geo thermostats
Author-email: Steve Garrity <sgarrity@gmail.com>
License: MIT License
Project-URL: Homepage, https://github.com/stgarrity/lux-geo-python
Project-URL: Repository, https://github.com/stgarrity/lux-geo-python
Requires-Python: >=3.7
License-File: LICENSE
Requires-Dist: aiohttp
Requires-Dist: pkce
Dynamic: license-file
